{
    "Artist": [
        "James Brown",
        "Lucinda Williams",
        "Willie Nelson",
        "Max Romeo & The Upsetters",
        "Freddie Hubbard",
        "Static-X",
        "Hatebreed",
        "Howlin' Wolf",
        "Earth, Wind & Fire",
        "Della Reese"
    ],
    "Title": [
        "I'll Go Crazy",
        "Joy",
        "Night Life ",
        "War Ina Babylon",
        "Red Clay",
        "Bled For Days",
        "Ghosts Of War",
        "Shake For Me",
        "Evil",
        "Don't You Know"
    ],
    "Lyric": [
        {
            "Lyrics": [
                [
                    "You know I feel all right",
                    "You know I feel all right, you're right",
                    "I feel all right",
                    "",
                    "If you leave me, I'll go crazy",
                    "If you leave me, I'll go crazy",
                    "Cause I love you, I love you",
                    "Oh, oh, I love you too much",
                    "",
                    "If you quit me, I'll go crazy",
                    "If you forget me, I'll go crazy",
                    "Cause I love you, I love you",
                    "Oh, oh, I love you too much",
                    "",
                    "You've got to live for yourself",
                    "Yourself and nobody else",
                    "You've got to live for yourself",
                    "Yourself and nobody else",
                    "",
                    "If you leave me, I'll go crazy",
                    "If you leave me, I'll go crazy",
                    "Cause I love you, I love you",
                    "Oh, oh, I love you too much",
                    "",
                    "You've got to live for yourself",
                    "Yourself and nobody else",
                    "You've got to live for yourself",
                    "Yourself and nobody else",
                    "",
                    "If you leave me, I'll go crazy",
                    "If you leave me, I'll go crazy",
                    "Cause I love you, I love you",
                    "Oh, oh, I love you too much"
                ]
            ],
            "Comments": [],
            "Title": "James\u00a0Brown \u2013 I'll Go Crazy | Genius"
        },
        {
            "Lyrics": [
                [
                    "[Verse 1]",
                    "I don't want you anymore",
                    "Cause you took my joy",
                    "I don't want you anymore",
                    "You took my joy",
                    "You took my joy",
                    "I want it back",
                    "You took my joy",
                    "I want it back",
                    "",
                    "[Verse 2]",
                    "I'm gonna go to West Memphis",
                    "And look for my joy",
                    "Go to West Memphis",
                    "And look for my joy",
                    "Maybe in West Memphis",
                    "I'll find my joy",
                    "Maybe in West Memphis",
                    "I'll find my joy",
                    "",
                    "[Verse 3]",
                    "I'm gonna go to Slidell",
                    "And look for my joy",
                    "Go to Slidell",
                    "And look for my joy",
                    "Maybe in Slidell",
                    "I'll find my joy",
                    "Maybe in Slidell",
                    "I'll find my joy",
                    "",
                    "[Verse 4]",
                    "You got no right to take my joy",
                    "I want it back",
                    "You got no right to take my joy",
                    "I want it back",
                    "You took my joy",
                    "I want it back",
                    "You took my joy",
                    "I want it back",
                    "",
                    "[Verse 5]",
                    "I'm gonna go to West Memphis",
                    "And look for my joy",
                    "Go to West Memphis",
                    "And look for my joy",
                    "Maybe in West Memphis",
                    "I'll find my joy",
                    "Maybe in West Memphis",
                    "I'll find my joy",
                    "",
                    "[Verse 6]",
                    "I'm gonna go to Slidell",
                    "And look for my joy",
                    "Go to Slidell",
                    "And look for my joy",
                    "Maybe in Slidell",
                    "I'll find my joy",
                    "Maybe in Slidell",
                    "I'll find my joy",
                    "",
                    "[Verse 7]",
                    "I don't want you anymore",
                    "Cause you took my joy",
                    "I don't want you anymore",
                    "You took my joy",
                    "You took my joy",
                    "I want it back",
                    "You took my joy",
                    "I want it back",
                    "You took my joy",
                    "I want it back",
                    "You took my joy",
                    "I want it back",
                    "",
                    "[Outro]",
                    "I'm gonna go to West Memphis",
                    "I'm gonna go to Slidell"
                ]
            ],
            "Comments": [],
            "Title": "Lucinda\u00a0Williams \u2013 Joy Lyrics | Genius Lyrics"
        },
        {
            "Lyrics": [
                [
                    "[Verse 1]",
                    "When the evening sun goes down",
                    "You will find me hanging round",
                    "The night life ain't no good life",
                    "But it's my life",
                    "",
                    "[Verse 2]",
                    "Many people just like me",
                    "Dreaming of old used-to-be's",
                    "And the night life ain't no good life",
                    "But it's my life",
                    "",
                    "[Bridge]",
                    "Listen to the blues they're playing",
                    "Listen to what the blues are saying",
                    "",
                    "[Verse 3]",
                    "My life is just another scene",
                    "From the world of broken dreams",
                    "And the night life ain't no good life",
                    "But it's my life",
                    "The night life ain't no good life",
                    "But it's my life"
                ]
            ],
            "Comments": [],
            "Title": "Willie\u00a0Nelson \u2013 Night Life Lyrics | Genius Lyrics"
        },
        {
            "Lyrics": [
                [
                    "It sipple out deh!",
                    "War inna babylon, tribal war inna Babylon",
                    "Let me tell, it sipple out deh",
                    "A wha' you seh, it sipple out deh, oh yeah",
                    "War inna babylon, tribal war inna Babylon",
                    "It sipple out deh, wha' you seh, it sipple out deh, oh yeah",
                    "",
                    "De baba men nuh like de dreadlocks man",
                    "De dreadlocks man nuh like de baba man, no",
                    "De po-lice men nuh like de dreadlocks man",
                    "De dreadlocks man nuh like de po-lice man, no",
                    "",
                    "So war inna babylon, tribal war inna Babylon",
                    "Let me tell, it sipple out deh",
                    "A wha' you seh, it sipple out deh, oh yeah",
                    "War inna babylon, tribal war inna Babylon",
                    "Let me tell, it sipple out deh",
                    "A wha' you seh, it sipple out deh, oh yeah",
                    "",
                    "When come pride then cometh shame",
                    "A man pride shall bring him low, yeah, oh yeah",
                    "Honour shall uphold the humble in spirit",
                    "And you know it's true, yeah , oh yeah",
                    "",
                    "War inna babylon, tribal war inna Babylon",
                    "A wha' you seh, it sipple out deh",
                    "So wha' fe do ? we slide out deh, oh yeah",
                    "War inna babylon, tribal war inna Babylon",
                    "A wha' you seh, it sipple out deh",
                    "So wha' fe do ? mek we slide out deh, oh yeah",
                    "",
                    "True, true, true, it sipple out deh",
                    "So wha' fe do ? mek we slide out deh, oh yeah",
                    "True, true, true, it sipple out deh",
                    "Let me tell, we slide out deh",
                    "",
                    "Marcus garvey prophecise, say:",
                    "\"One mus' live 10 miles away, yeah, in this time\"",
                    "I-man satta at the mountain top",
                    "Watching Babylon burning red hot, red hot",
                    "",
                    "War inna babylon, tribal war inna Babylon",
                    "A wha' you seh, it sipple out deh",
                    "So wha' fe do ? we slide out deh, oh yeah",
                    "War inna babylon, tribal war inna Babylon",
                    "A wha' you seh, it sipple out deh",
                    "So wha' fe do ? mek we slide out deh, oh yeah",
                    "",
                    "True, true, true, it sipple out deh",
                    "So wha' fe do ? mek we slide out deh, oh yeah",
                    "True, true, true, it sipple out deh",
                    "Let me tell, we slide out deh"
                ]
            ],
            "Comments": [],
            "Title": "Max\u00a0Romeo & The Upsetters \u2013 War In A Babylon Lyrics | Genius Lyrics"
        },
        {
            "Lyrics": [
                [
                    "If you told me that you loved me I would feel so proud",
                    "Let me hold you honey, I'd holler out loud",
                    "Never love another even if I can",
                    "Come to me baby I'm a one woman man",
                    "",
                    "Now won't you love me baby just to kinda hang around",
                    "I'll always love you honey, I'll never let you down",
                    "Never love another even if I can",
                    "Come to me baby I'm a one woman man",
                    "",
                    "Well I'd climb the highest mountain if it reached the sky",
                    "To prove that I love you I'd jump off and fly",
                    "I'd even swim the ocean from shore to shore",
                    "To prove that I love you just a little bit more",
                    "",
                    "Ah won't you love me baby just to kinda hang around",
                    "I'll always love you honey, I'll never let you down",
                    "Never love another even if I can",
                    "Come to me baby I'm a one woman man",
                    "",
                    "Now won't you love me baby just to kinda hang around",
                    "I'll always love you honey, I'll never let you down",
                    "Never love another even if I can",
                    "Come to me baby I'm a one woman man",
                    "",
                    "Come to me baby I'm a one woman man",
                    "Come to me baby I'm a one woman man"
                ]
            ],
            "Comments": [],
            "Title": "Freddie\u00a0Hubbard \u2013 Red Clay Lyrics | Genius Lyrics"
        },
        {
            "Lyrics": [
                [
                    "Meaningless, it's meaningless",
                    "It's meaningless, it's meaningless",
                    "I take the hold, I take the hold",
                    "I take the hold, I take the hold",
                    "",
                    "Mindlessness, it's mindlessness",
                    "It's mindlessness, it's mindlessness",
                    "I bled for days, I bled for days",
                    "I bled for days, I bled for days",
                    "",
                    "Get to the race, the healing of it fucking with",
                    "Conceal the scab, you don't want to show",
                    "Into the hate, I channel all the negative and",
                    "I bled for days now I take the hold, go",
                    "",
                    "Get to the race, the healing of it fucking with",
                    "Conceal the scab, you don't want to show",
                    "Into the hate I channel all the negative and",
                    "I bled for days now I take the hold",
                    "",
                    "I don't believe it, fuck me, read me, get me, bled for days",
                    "Smile on my rage I'm scarred by age, I bled for days",
                    "",
                    "Uselessness, it's uselessness",
                    "It's uselessness, it's uselessness",
                    "Make my weapons, make my weapons",
                    "Make my weapons, take the hold",
                    "",
                    "I don't believe it, fuck me, read me, get me, bled for days",
                    "Smile on my rage I'm scarred by age, I bled for days",
                    "I don't believe it, fuck me, read me, get me, bled for days",
                    "Smile on my rage I'm, scarred by age, I bled for days",
                    "",
                    "Bled for days, bled for days",
                    "",
                    "Get to the race, the healing of it fucking with",
                    "Conceal the scab you don't want to show",
                    "Into the hate I channel all the negative and",
                    "I bled for days now I take the hold",
                    "",
                    "Get to the race, the healing of it fucking with",
                    "Conceal the scab you don't want to show",
                    "Into the hate I channel all the negative and",
                    "I bled for days now I take the hold"
                ]
            ],
            "Comments": [],
            "Title": "Static-X \u2013 Bled for Days Lyrics | Genius Lyrics"
        },
        {
            "Lyrics": [
                [
                    "Fate silent warriors sleeping souls will arise",
                    "Once forgotten soldiers come to life",
                    "Fallen mercenary, dormancy is done",
                    "Not content with wars we never won",
                    "",
                    "Memories can't ignore",
                    "Anguish of before",
                    "Satisfy the scorn",
                    "Rise ghosts of war",
                    "",
                    "Target assassinate, time of your life has expired",
                    "Hatred victimize, gaze in their eyes as they die",
                    "Violence inflicting of pain, savage morticians deny",
                    "Drive the salt in the wound, arouse the subconscious to lie",
                    "",
                    "Memories can't ignore",
                    "Anguish of before",
                    "Satisfy the scorn",
                    "Rise ghosts of war",
                    "",
                    "I deal in pain",
                    "All life I drain",
                    "I dominate",
                    "I seal your fate",
                    "",
                    "I deal in pain",
                    "All life I drain",
                    "Memories can't ignore",
                    "Rise ghost of war"
                ]
            ],
            "Comments": [],
            "Title": "Hatebreed \u2013 Ghosts of War Lyrics | Genius Lyrics"
        },
        {
            "Lyrics": [
                [
                    "Sure look good",
                    "But it don't mean a thing to me",
                    "Sure look good",
                    "But it don't mean a thing to me",
                    "I got a hip-shaking woman",
                    "Shake like a willow tree",
                    "You better wait, baby",
                    "You got back a little too late",
                    "You better wait, baby",
                    "You got back a little too late",
                    "I got a cool-shaking baby",
                    "Shake like jello on a plate",
                    "When my baby walk",
                    "You know she's fine and mellow",
                    "When my baby walk",
                    "You know she's fine and mellow",
                    "Every time she stops",
                    "Her flesh it shake like jello",
                    "Oh, shake it baby, shake it for me",
                    "Oh, shake lil' baby, shake it for me",
                    "Oh, shake it little baby, shake it like a willow tree",
                    "The way you shake it"
                ]
            ],
            "Comments": [],
            "Title": "Howlin'\u00a0Wolf \u2013 Shake for Me Lyrics | Genius Lyrics"
        },
        {
            "Lyrics": [
                [
                    "Evil runnin' through our brain",
                    "We and evil is about the same",
                    "",
                    "Bad blood through our body flows",
                    "Where's the love nobody knows?",
                    "(Nobody knows)",
                    "(Nobody knows)",
                    "(Nobody knows)",
                    "",
                    "Beauty in our face you see",
                    "Tryin' to hide all our misery",
                    "(Our misery)",
                    "(Our misery)",
                    "(Our misery)",
                    "",
                    "But evil runnin' through our brain",
                    "We and evil are about the same, oh yeah",
                    "",
                    "Evil... in our life",
                    "Evil... causin' strife, yeah yeah",
                    "(Evil)",
                    "",
                    "Lookin' for a place to guide",
                    "A little light in our souls and minds, oh yeah",
                    "",
                    "Maybe if we learn to pray",
                    "Life would give us sunshiny days",
                    "(Sunshiny days)",
                    "(Sunshiny days)",
                    "(Sunshiny days)",
                    "",
                    "And evil, it's runnin' through our brains",
                    "Turn to love and won't be the blame",
                    "(Won't be the blame)",
                    "(Won't be the blame)",
                    "(Won't be the blame)",
                    "",
                    "Evil... in our life",
                    "Evil... causin' strife",
                    "(Evil)"
                ]
            ],
            "Comments": [],
            "Title": "Earth,\u00a0Wind & Fire \u2013 Evil Lyrics | Genius Lyrics"
        },
        {
            "Lyrics": [
                [
                    "Don't you know",
                    "I have fallen in love with you",
                    "For the rest of my whole life through",
                    "",
                    "Don't you know",
                    "I was yours from the very day",
                    "That you happened to come my way",
                    "",
                    "Can't you see",
                    "I'm under your spell",
                    "By the look in my eyes",
                    "Can't you tell, can't you tell",
                    "",
                    "Now, don't you know",
                    "Every beat of my heart keeps crying out",
                    "I love you so",
                    "Don't you know",
                    "",
                    "Don't you know",
                    "Every beat of my heart keeps crying out",
                    "I love you so",
                    "Don't you know"
                ]
            ],
            "Comments": [],
            "Title": "Della\u00a0Reese \u2013 Don't You Know Lyrics | Genius Lyrics"
        }
    ],
    "Mood": [
        "happy",
        "happy",
        "happy",
        "angry",
        "happy",
        "angry",
        "angry",
        "relaxed",
        "angry",
        "happy"
    ]
}